setup.py
i2py/__init__.py
i2py.egg-info/PKG-INFO
i2py.egg-info/SOURCES.txt
i2py.egg-info/dependency_links.txt
i2py.egg-info/pbr.json
i2py.egg-info/requires.txt
i2py.egg-info/top_level.txt
i2py/control/__init__.py
i2py/control/__main__.py
i2py/control/control.py
i2py/control/pyjsonrpc/__init__.py
i2py/control/pyjsonrpc/cp.py
i2py/control/pyjsonrpc/http.py
i2py/control/pyjsonrpc/rpcerror.py
i2py/control/pyjsonrpc/rpcjson.py
i2py/control/pyjsonrpc/rpclib.py
i2py/control/pyjsonrpc/rpcrequest.py
i2py/control/pyjsonrpc/rpcresponse.py
i2py/netdb/__init__.py
i2py/netdb/__main__.py
i2py/netdb/netdb.py