Metadata-Version: 1.1
Name: i2py
Version: 0.3.1
Summary: Tools to work with i2p.
Home-page: https://github.com/chris-barry/i2py
Author: See contributors.txt
Author-email: Anonymous
License: UNKNOWN
Platform: UNKNOWN
Classifier: Development Status :: 3 - Alpha
Classifier: License :: OSI Approved :: MIT License
Classifier: Intended Audience :: Developers
Classifier: Topic :: Utilities
